<?xml version="1.0"?>
<slideshow title="EyeView">
	<documentinfo>
		<author>EyeHouse</author>
		<version>1.0</version>
		<comment>Private Student Housing Software</comment>
		<groupid>5</groupid>
	</documentinfo>
	<defaultsettings>
		<backgroundcolor>#00000000</backgroundcolor>
		<font>Calibri</font>
		<fontsize>12</fontsize>
		<fontcolor>#ffcccc00</fontcolor>
	</defaultsettings>
	<slide id="0" title="Start Page" duration="0">
	</slide>
	<slide id="1" title="Logged Out Home" duration="0">
		<graphic type="rectangle" xstart="0.0" ystart="0.0" xend="0.19" yend="1.0" solid="true" graphiccolor="#FF7AA9DD" duration="0" />
	</slide>
	<slide id="2" title="Logged In Home" duration="0">
		<graphic type="rectangle" xstart="0.0" ystart="0.0" xend="0.19" yend="1.0" solid="true" graphiccolor="#FF7AA9DD" duration="0" />
	</slide>
	<slide id="3" title="Login Slide" duration="0">
		<graphic type="rectangle" xstart="0.0" ystart="0.0" xend="0.19" yend="1.0" solid="true" graphiccolor="#FF7AA9DD" duration="0" />
	</slide>
	<slide id="4" title="Register Slide" duration="0">
		<graphic type="rectangle" xstart="0.0" ystart="0.0" xend="0.19" yend="1.0" solid="true" graphiccolor="#FF7AA9DD" duration="0" />
	</slide>
	<slide id="5" title="Video Slide" duration="0">
		<graphic type="rectangle" xstart="0.0" ystart="0.0" xend="0.19" yend="1.0"
			duration="0" graphiccolor="#FF7AA9DD" solid="true">
		</graphic>
	</slide>
	<slide id="6" title="Profile Slide" duration="0">
		<graphic type="rectangle" xstart="0.0" ystart="0.0" xend="0.19" yend="1.0" solid="true" graphiccolor="#FF7AA9DD" duration="0" />
	</slide>
	<slide id="7" title="Account Settings Slide" duration="0">
		<graphic type="rectangle" xstart="0.0" ystart="0.0" xend="0.19" yend="1.0" solid="true" graphiccolor="#FF7AA9DD" duration="0" />
	</slide>
	<slide id="8" title="Saved Properties Slide" duration="0">
		<graphic type="rectangle" xstart="0.0" ystart="0.0" xend="0.19" yend="1.0" solid="true" graphiccolor="#FF7AA9DD" duration="0" />
	</slide>
	<slide id="9" title="House Slide" duration="0">
		<graphic type="rectangle" xstart="0.0" ystart="0.0" xend="0.19" yend="1.0" solid="true" graphiccolor="#FF7AA9DD" duration="0" />
	</slide>
	<slide id="10" title="More Info Slide" duration="0">
		<graphic type="rectangle" xstart="0.0" ystart="0.0" xend="0.19" yend="1.0" solid="true" graphiccolor="#FF7AA9DD" duration="0" />
	</slide>
	<slide id="11" title="Review Slide" duration="0">
		<graphic type="rectangle" xstart="0.0" ystart="0.0" xend="0.19" yend="1.0" solid="true" graphiccolor="#FF7AA9DD" duration="0" />
	</slide>
	<slide id="12" title="Map Slide" duration="0">
		<graphic type="rectangle" xstart="0.0" ystart="0.0" xend="0.19" yend="1.0" solid="true" graphiccolor="#FF7AA9DD" duration="0" />
	</slide>
	<slide id="13" title="Landlord Properties Slide" duration="0">
		<graphic type="rectangle" xstart="0.0" ystart="0.0" xend="0.19" yend="1.0" solid="true" graphiccolor="#FF7AA9DD" duration="0" />
	</slide>
	<slide id="14" title="Edit Property Slide" duration="0">
		<graphic type="rectangle" xstart="0.0" ystart="0.0" xend="0.19" yend="1.0" solid="true" graphiccolor="#FF7AA9DD" duration="0" />
	</slide>
	<slide id="15" title="Search Results Slide" duration="0">
		<graphic type="rectangle" xstart="0.0" ystart="0.0" xend="0.19" yend="1.0" solid="true" graphiccolor="#FF7AA9DD" duration="0" />
	</slide>
</slideshow>